{
  "app_name": "Kpop Piano Beats - Music Game for Android - Free App Download",
  "package_name": "com.ningningstudio.kpopmagictiles",
  "Total downloads": "20 million",
  "Recent downloads": "900 thousand",
  "Rating": "4.59 based on 88 thousand ratings",
  "Ranking": "Top ranked",
  "APK size": "114.9 MB",
  "Designed for Android": "8.0+",
  "Suitable for": "Everyone",
  "Ads": "Contains ads",
  "developer_info": {
    "name": "Sonata Studio",
    "email": "lan.kpop@outlook.com",
    "website": "https://kpopmagictiles.netlify.app/app-ads.txt"
  },
  "about_section": "Kpop Piano Beats - Music Game is a music game developed by Sonata Studio. The APK has been available since August 2023 . In the last 30 days, the app was downloaded about 900 thousand times. It's top ranked. It's rated 4.59 out of 5 stars, based on 88 thousand ratings. The last update of the app was on May 16, 2025 . Kpop Piano Beats - Music Game has a content rating \"Everyone\" . Kpop Piano Beats - Music Game has an APK download size of 114.90 MB and the latest version available is 4.3.0 . Designed for Android version 8.0+ . Kpop Piano Beats - Music Game is FREE to download.",
  "app_description": "Get ready for 'Kpop Piano Beats-  blackpink the game' It's a fun game where you tap along to awesome Kpop songs. Imagine dancing to the coolest music hits with stray kids and more.\nHow to play?\n\ud83c\udfb6 Dance to the Beat:\nTap, slide, and hold the tiles to match the music's beat. It's like dancing with your fingers! Feel like a Kpop idol as you play.\nOur key features:\n\ud83c\udf1f Latest Kpop Hits:\nPlay with the newest Kpop songs. The game is always updated with the most popular song from the most artists, girl bands, boy bands: Jung Kook, Black Pink, NewJeans, BTS, Big Bang, SNSD, Aespa, Stray Kids, Twice, ITZY, .... It's like having your own Kpop concert!\n\ud83d\udd25 Super Fun to Play:\nIt's like a challenge! Tap the tiles and keep up with the music. You can choose how hard or easy you want it to be. How good are your dancing skills?\n\ud83d\udc7dEnjoy the endless\nEndless mode is available! Could you beat your best score?\n\ud83c\udf89 Collect and Make It Yours:\nAs you play, you can unlock cool stuff to make the game look awesome. You can even choose different looks that remind you of Kpop. It's your game, your style!\n\ud83c\udfc6 Play with Friends:\nWant to show off your dancing talent? Play with friends and others from far away. See who can get the highest score and be the best dancer!\nReady to dance to Kpop music? 'Kpop Piano Beats- Music Game' is all about music, fun, and dancing. Download it now and let's get the party started!\nNote: If any producer or label has an issue with any of the music used in the game, please send email to us and it will be deleted immediately if necessary (this includes the images used).\nRecent changes:\nDiscover our stunning new visual updates!",
  "api_details": {
    "permissions": {},
    "technologies": {
      "Ad network libraries": [
        "AdMob",
        "Facebook Audience Network",
        "Unity Ads",
        "Open Measurement",
        "AppLovin",
        "AppsFlyer",
        "Ironsource",
        "InMobi",
        "Chartboost",
        "Amazon Mobile Ads",
        "Tapjoy"
      ],
      "Social libraries": [
        "Facebook"
      ],
      "Development tools": [
        "Android Jetpack core",
        "Android Architecture Components",
        "Android Jetpack VersionedParcelable",
        "Firebase",
        "Android Jetpack Annotations",
        "Android Jetpack Widgets",
        "Android Jetpack AppCompat",
        "AndroidX Activity",
        "Android Activity Saved State",
        "AndroidX Loader",
        "Android Jetpack Media",
        "Google Cloud Messaging (GCM)",
        "Android Transition Support Library",
        "Android Support Library collections",
        "Android Support VectorDrawable",
        "AndroidX Legacy: Support Library core utils",
        "Kotlin",
        "AndroidX Cursor Adapter",
        "AndroidX Local Broadcast Manager",
        "Android Support Library Print",
        "Android Support Library Document File",
        "AndroidX Legacy: Support Library core UI",
        "Google gson",
        "Android Support Library Async Layout Inflater",
        "Android WorkManager",
        "Okio",
        "JetBrains Annotations",
        "IntelliJ IDEA",
        "AndroidX ExifInterface",
        "Google ZXing",
        "Picasso",
        "Chromium",
        "Google Guava",
        "BoltsFramework",
        "Google Protocol Buffers",
        "Unity 3D",
        "FMOD Ex Programmers API",
        "The Checker Framework",
        "Grpc",
        "RevenueCat"
      ]
    },
    "raw_html_snippet": "<div>\n    <h2>\n        Permissions\n    </h2>\n    \n        <div class=\"row app-permissions\">\n            \n                <div class=\"col-sm-6 col-lg-4\">\n                    <div class=\"default-box-color vpadding-xs hpadding-s\">\n                        <b>Network communication</b>\n                        <div>\n                            \n                                view network connections,\n                            \n                                view Wi-Fi connections,\n                            \n                                full network access,\n                            \n                                Google Play billing service,\n                            \n                                receive data from Internet\n                            \n                        </div>\n                    </div>\n                </div>\n            \n                <div class=\"col-sm-6 col-lg-4\">\n                    <div class=\"default-box-color vpadding-xs hpadding-s\">\n           ..."
  },
  "changelog": [
    {
      "date": "May 16, 2025",
      "type": "Update",
      "description": "Version 4.4.1"
    },
    {
      "date": "Apr 28, 2025",
      "type": "Update",
      "description": "Version 4.4.0"
    },
    {
      "date": "Mar 26, 2025",
      "type": "Update",
      "description": "Version 4.3.0"
    },
    {
      "date": "Feb 6, 2025",
      "type": "Update",
      "description": "Version 4.2.2"
    },
    {
      "date": "Jan 6, 2025",
      "type": "Update",
      "description": "Version 4.2.1"
    },
    {
      "date": "Dec 19, 2024",
      "type": "Update",
      "description": "Version 4.2.0"
    },
    {
      "date": "Nov 12, 2024",
      "type": "Update",
      "description": "Version 4.0.5"
    },
    {
      "date": "Nov 4, 2024",
      "type": "Update",
      "description": "Version 4.0.4"
    },
    {
      "date": "Nov 4, 2024",
      "type": "Update",
      "description": "Version 4.0.4"
    },
    {
      "date": "Oct 10, 2024",
      "type": "Update",
      "description": "Version 3.9.4"
    },
    {
      "date": "Oct 4, 2024",
      "type": "Update",
      "description": "Version 3.9.3"
    },
    {
      "date": "Sep 20, 2024",
      "type": "Update",
      "description": "Version 3.9.0"
    },
    {
      "date": "Sep 15, 2024",
      "type": "Installs",
      "description": "10,000,000+ installs"
    },
    {
      "date": "Aug 13, 2024",
      "type": "Update",
      "description": "Version 3.8.0"
    },
    {
      "date": "Jul 23, 2024",
      "type": "Update",
      "description": "Version 3.6.1"
    },
    {
      "date": "Jul 19, 2024",
      "type": "Update",
      "description": "Version 3.5.1"
    },
    {
      "date": "Jun 24, 2024",
      "type": "Update",
      "description": "Version 3.5.0"
    },
    {
      "date": "Jun 10, 2024",
      "type": "Update",
      "description": "Version 3.4.0"
    },
    {
      "date": "May 29, 2024",
      "type": "Update",
      "description": "Version 3.3.1"
    },
    {
      "date": "May 26, 2024",
      "type": "Update",
      "description": "Version 3.3.0"
    },
    {
      "date": "May 15, 2024",
      "type": "Update",
      "description": "Version 3.2.1"
    },
    {
      "date": "May 10, 2024",
      "type": "Update",
      "description": "Version 3.2.0"
    },
    {
      "date": "May 10, 2024",
      "type": "Installs",
      "description": "5,000,000+ installs"
    },
    {
      "date": "Mar 15, 2024",
      "type": "Update",
      "description": "Version 2.8.2"
    },
    {
      "date": "Mar 11, 2024",
      "type": "Update",
      "description": "Version 2.8.0"
    },
    {
      "date": "Mar 3, 2024",
      "type": "Update",
      "description": "Version 2.7.0"
    },
    {
      "date": "Feb 22, 2024",
      "type": "Update",
      "description": "Version 2.6.0"
    },
    {
      "date": "Jan 29, 2024",
      "type": "Update",
      "description": "Version 2.5.0"
    },
    {
      "date": "Jan 22, 2024",
      "type": "Update",
      "description": "Version 2.4.0"
    },
    {
      "date": "Jan 17, 2024",
      "type": "Update",
      "description": "Version 2.3.0"
    },
    {
      "date": "Jan 14, 2024",
      "type": "Update",
      "description": "Version 2.2.1"
    },
    {
      "date": "Jan 9, 2024",
      "type": "Update",
      "description": "Version 2.2.0"
    },
    {
      "date": "Jan 4, 2024",
      "type": "Update",
      "description": "Version 2.1.0"
    },
    {
      "date": "Dec 29, 2023",
      "type": "Update",
      "description": "Version 1.0.11"
    },
    {
      "date": "Dec 11, 2023",
      "type": "Update",
      "description": "Version 1.0.10"
    },
    {
      "date": "Nov 30, 2023",
      "type": "Installs",
      "description": "1,000,000+ installs"
    },
    {
      "date": "Nov 24, 2023",
      "type": "Update",
      "description": "Version 1.0.9"
    },
    {
      "date": "Nov 10, 2023",
      "type": "Update",
      "description": "Version 1.0.8"
    },
    {
      "date": "Nov 8, 2023",
      "type": "Installs",
      "description": "500,000+ installs"
    },
    {
      "date": "Nov 3, 2023",
      "type": "Update",
      "description": "Version 1.0.7"
    },
    {
      "date": "Oct 25, 2023",
      "type": "Update",
      "description": "Version 1.0.6"
    },
    {
      "date": "Oct 23, 2023",
      "type": "Installs",
      "description": "100,000+ installs"
    },
    {
      "date": "Oct 9, 2023",
      "type": "Installs",
      "description": "50,000+ installs"
    },
    {
      "date": "Oct 6, 2023",
      "type": "Update",
      "description": "Version 1.0.5"
    },
    {
      "date": "Sep 25, 2023",
      "type": "Installs",
      "description": "5,000+ installs"
    },
    {
      "date": "Sep 21, 2023",
      "type": "Update",
      "description": "Version 1.0.4"
    },
    {
      "date": "Sep 13, 2023",
      "type": "Installs",
      "description": "5+ installs"
    },
    {
      "date": "Sep 8, 2023",
      "type": "Update",
      "description": "Version 1.0.2"
    },
    {
      "date": "Aug 30, 2023",
      "type": "New App",
      "description": "Version 1.0.0 in MUSIC for Free"
    }
  ],
  "country": "Vietnam",
  "category": "Game",
  "status": "success",
  "url": "https://www.appbrain.com/app/body-color-swap/com.ningningstudio.kpopmagictiles",
  "timestamp": "2025-06-12T02:33:02.048512",
  "categories": "Game, Music",
  "downloads": 57344,
  "is_ad": "YES",
  "is_pub": "YES",
  "market_url": "https://play.google.com/store/apps/details?hl=en_US&gl=us&id=com.ningningstudio.kpopmagictiles",
  "name": "Kpop Piano Beats - Music Game",
  "platform": "Android",
  "position": 711,
  "publisher_contacts": "publisher@greedygame.com, lan.kpop@outlook.com",
  "publisher_name": "Sonata Studio",
  "publisher_website": "https://kpopmagictiles.netlify.app/app-ads.txt",
  "release_date": "2023-08-30",
  "revenue_usd": 78,
  "rpd": 0.001
}